paracuda/__init__.py
paracuda/__version__.py
paracuda/decorators.py
paracuda/devices.py
paracuda/paracuda_run.py
paracuda/utils.py
paracuda/tests/__init__.py
paracuda/tests/test_decorators.py
paracuda/tests/test_utils.py
paracuda-0.3.0.dist-info/licenses/LICENCE.md
paracuda-0.3.0.dist-info/METADATA
paracuda-0.3.0.dist-info/WHEEL
paracuda-0.3.0.dist-info/entry_points.txt
paracuda-0.3.0.dist-info/top_level.txt
paracuda-0.3.0.dist-info/RECORD
