Metadata-Version: 2.4
Name: ParaCuda
Version: 0.3.0
Summary: ParaCuda - Parallel Execution of CUDA hyperparameter sweeps in Python for pytorch and beyond.
Author-email: Sven Giese <sven.giese88@gmail.com>
License: MIT
Project-URL: Homepage, https://github.com/gieses/ParaCuda
Project-URL: Documentation, https://github.com/gieses/ParaCuda
Keywords: cuda,parallel,gpu,scripting,execution,performance
Requires-Python: >=3.9
License-File: LICENCE.md
Requires-Dist: loguru
Requires-Dist: tqdm
Requires-Dist: torch
Requires-Dist: pandas
Requires-Dist: pyarrow
Requires-Dist: scikit-learn
Provides-Extra: dev
Requires-Dist: pytest; extra == "dev"
Requires-Dist: ruff; extra == "dev"
Requires-Dist: build; extra == "dev"
Requires-Dist: twine; extra == "dev"
Dynamic: license-file
